database_converter/__init__.py
database_converter/converters/__init__.py
database_converter/converters/db.py
database_converter/converters/sqlite3/__init__.py
database_converter/converters/sqlite3/db.py
database_converter/decoders/__init__.py
database_converter/decoders/json.py
database_converter/decoders/protobuf.py
database_converter/readers/__init__.py
database_converter/readers/json.py
database_converter/readers/xml.py
database_converter/utils/__init__.py
database_converter/utils/constants.py
database_converter/utils/logger.py
database_converter/utils/utils.py
database_converter/writers/__init__.py
database_converter/writers/json.py
database_converter/writers/xml.py
database_converter-0.0.7.1.dist-info/METADATA
database_converter-0.0.7.1.dist-info/WHEEL
database_converter-0.0.7.1.dist-info/licenses/LICENSE
database_converter-0.0.7.1.dist-info/RECORD
