Metadata-Version: 2.3
Name: database-converter
Version: 0.0.7.1
Project-URL: Repository, https://github.com/consithe1/database_utils
Author: consithe1
License: MIT License
License-File: LICENSE
Keywords: database,extraction,json,sqlite3,xml
Requires-Python: >=3.8
Requires-Dist: blackboxprotobuf~=1.0.1
Requires-Dist: func-timeout~=4.3.5
